planetra_solver/__init__.py
solver/__init__.py
planetra_planetra_solver-0.1.3.dist-info/METADATA
planetra_planetra_solver-0.1.3.dist-info/WHEEL
planetra_planetra_solver-0.1.3.dist-info/top_level.txt
planetra_planetra_solver-0.1.3.dist-info/RECORD
