Metadata-Version: 2.1
Name: planetra-planetra_solver
Version: 0.1.3
Summary: The library contains basic functions that can help in Planetra development
Home-page: https://planetra.gitlab.yandexcloud.net/testgroup/planetra_solver.git
Author: Anton Vyugin, Ruslan Gafurov
Author-email: anton.vyugin.00@mail.ru, g.r.9@mail.ru
License: MIT
Classifier: Programming Language :: Python :: 3
Classifier: License :: OSI Approved :: MIT License
Classifier: Operating System :: OS Independent
Requires-Python: >=3.6
